[{"actions": [{"actionCode": "Intro-H", "actionDate": "2021-01-03", "sourceSystem": {"code": 9, "name": "Library of Congress"}, "text": "Introduced in House", "type": "IntroReferral"}, {"actionCode": "1000", "actionDate": "2021-01-03", "sourceSystem": {"code": 9, "name": "Library of Congress"}, "text": "Introduced in House", "type": "IntroReferral"}], "pagination": {"count": 2}, "request": {"billNumber": "16", "billType": "hr", "billUrl": "https://api.congress.gov/v3/bill/117/hr/16?format=json", "congress": "117", "contentType": "application/json", "format": "json"}}, 200]