[{"actions": [{"actionCode": "H11000", "actionDate": "2021-05-21", "committees": [{"name": "Livestock, Dairy, and Poultry Subcommittee", "systemCode": "hsag29", "url": "https://api.congress.gov/v3/committee/house/hsag29?format=json"}], "sourceSystem": {"code": 1, "name": "House committee actions"}, "text": "Referred to the Subcommittee on Livestock and Foreign Agriculture.", "type": "Committee"}, {"actionCode": "H11100", "actionDate": "2021-03-18", "committees": [{"name": "Agriculture Committee", "systemCode": "hsag00", "url": "https://api.congress.gov/v3/committee/house/hsag00?format=json"}], "sourceSystem": {"code": 2, "name": "House floor actions"}, "text": "Referred to the House Committee on Agriculture.", "type": "IntroReferral"}, {"actionCode": "Intro-H", "actionDate": "2021-03-18", "sourceSystem": {"code": 9, "name": "Library of Congress"}, "text": "Introduced in House", "type": "IntroReferral"}, {"actionCode": "1000", "actionDate": "2021-03-18", "sourceSystem": {"code": 9, "name": "Library of Congress"}, "text": "Introduced in House", "type": "IntroReferral"}], "pagination": {"count": 4}, "request": {"billNumber": "1998", "billType": "hr", "billUrl": "https://api.congress.gov/v3/bill/117/hr/1998?format=json", "congress": "117", "contentType": "application/json", "format": "json"}}, 200]