{"actions": {"count": 4, "url": "https://api.congress.gov/v3/bill/117/hr/38/actions?format=json"}, "committees": {"count": 1, "url": "https://api.congress.gov/v3/bill/117/hr/38/committees?format=json"}, "congress": 117, "constitutionalAuthorityStatementText": "<pre>\n[Congressional Record Volume 167, Number 2 (Monday, January 4, 2021)]\n[House]\nFrom the Congressional Record Online through the Government Publishing Office [<a href=\"https://www.gpo.gov\">www.gpo.gov</a>]\nBy Mr. HUDSON:\nH.R. 38.\nCongress has the power to enact this legislation pursuant\nto the following:\nArticle I, Section 8\n[Page H52]\n</pre>", "cosponsors": {"count": 203, "countIncludingWithdrawnCosponsors": 203, "url": "https://api.congress.gov/v3/bill/117/hr/38/cosponsors?format=json"}, "introducedDate": "2021-01-04", "latestAction": {"actionDate": "2021-03-01", "text": "Referred to the Subcommittee on Crime, Terrorism, and Homeland Security."}, "number": "38", "originChamber": "House", "originChamberCode": "H", "policyArea": {"name": "Crime and Law Enforcement"}, "relatedBills": {"count": 2, "url": "https://api.congress.gov/v3/bill/117/hr/38/relatedbills?format=json"}, "sponsors": [{"bioguideId": "H001067", "district": 8, "firstName": "Richard", "fullName": "Rep. Hudson, Richard [R-NC-8]", "isByRequest": "N", "lastName": "Hudson", "party": "R", "state": "NC", "url": "https://api.congress.gov/v3/member/H001067?format=json"}], "subjects": {"count": 11, "url": "https://api.congress.gov/v3/bill/117/hr/38/subjects?format=json"}, "summaries": {"count": 1, "url": "https://api.congress.gov/v3/bill/117/hr/38/summaries?format=json"}, "textVersions": {"count": 1, "url": "https://api.congress.gov/v3/bill/117/hr/38/text?format=json"}, "title": "Concealed Carry Reciprocity Act", "titles": {"count": 3, "url": "https://api.congress.gov/v3/bill/117/hr/38/titles?format=json"}, "type": "HR", "updateDate": "2023-01-11T13:43:32Z", "updateDateIncludingText": "2023-01-11T13:43:32Z"}