{"actions": {"count": 5, "url": "https://api.congress.gov/v3/bill/117/hr/69/actions?format=json"}, "committees": {"count": 1, "url": "https://api.congress.gov/v3/bill/117/hr/69/committees?format=json"}, "congress": 117, "constitutionalAuthorityStatementText": "<pre>\n[Congressional Record Volume 167, Number 2 (Monday, January 4, 2021)]\n[House]\nFrom the Congressional Record Online through the Government Publishing Office [<a href=\"https://www.gpo.gov\">www.gpo.gov</a>]\nBy Mr. BUCHANAN:\nH.R. 69.\nCongress has the power to enact this legislation pursuant\nto the following:\nArticle I, Section 8, clause 3 provides Congress with the\npower to ``regulate commerce with foreign nations, and among\nthe several states, and with the Indian tribes.''\n[Page H52]\n</pre>", "cosponsors": {"count": 48, "countIncludingWithdrawnCosponsors": 48, "url": "https://api.congress.gov/v3/bill/117/hr/69/cosponsors?format=json"}, "introducedDate": "2021-01-04", "latestAction": {"actionDate": "2022-12-15", "text": "Motion to Discharge Committee filed by Mr. Mooney. Petition No: 117-18."}, "number": "69", "originChamber": "House", "originChamberCode": "H", "policyArea": {"name": "Science, Technology, Communications"}, "relatedBills": {"count": 1, "url": "https://api.congress.gov/v3/bill/117/hr/69/relatedbills?format=json"}, "sponsors": [{"bioguideId": "B001260", "district": 16, "firstName": "Vern", "fullName": "Rep. Buchanan, Vern [R-FL-16]", "isByRequest": "N", "lastName": "Buchanan", "party": "R", "state": "FL", "url": "https://api.congress.gov/v3/member/B001260?format=json"}], "subjects": {"count": 3, "url": "https://api.congress.gov/v3/bill/117/hr/69/subjects?format=json"}, "summaries": {"count": 1, "url": "https://api.congress.gov/v3/bill/117/hr/69/summaries?format=json"}, "textVersions": {"count": 1, "url": "https://api.congress.gov/v3/bill/117/hr/69/text?format=json"}, "title": "Sunshine Protection Act of 2021", "titles": {"count": 3, "url": "https://api.congress.gov/v3/bill/117/hr/69/titles?format=json"}, "type": "HR", "updateDate": "2024-02-05T14:30:09Z", "updateDateIncludingText": "2024-02-05T14:30:09Z"}