{"actions": {"count": 13, "url": "https://api.congress.gov/v3/bill/117/hr/151/actions?format=json"}, "committees": {"count": 6, "url": "https://api.congress.gov/v3/bill/117/hr/151/committees?format=json"}, "congress": 117, "constitutionalAuthorityStatementText": "<pre>\n[Congressional Record Volume 167, Number 2 (Monday, January 4, 2021)]\n[House]\nFrom the Congressional Record Online through the Government Publishing Office [<a href=\"https://www.gpo.gov\">www.gpo.gov</a>]\nBy Mr. QUIGLEY:\nH.R. 151.\nCongress has the power to enact this legislation pursuant\nto the following:\nArticle 1, Section 8, Clause 3 of the U.S. Constitution\n[Page H55]\n</pre>", "cosponsors": {"count": 188, "countIncludingWithdrawnCosponsors": 188, "url": "https://api.congress.gov/v3/bill/117/hr/151/cosponsors?format=json"}, "introducedDate": "2021-01-04", "latestAction": {"actionDate": "2021-03-04", "text": "Referred to the Subcommittee on Crime, Terrorism, and Homeland Security."}, "number": "151", "originChamber": "House", "originChamberCode": "H", "policyArea": {"name": "International Affairs"}, "relatedBills": {"count": 1, "url": "https://api.congress.gov/v3/bill/117/hr/151/relatedbills?format=json"}, "sponsors": [{"bioguideId": "Q000023", "district": 5, "firstName": "Mike", "fullName": "Rep. Quigley, Mike [D-IL-5]", "isByRequest": "N", "lastName": "Quigley", "party": "D", "state": "IL", "url": "https://api.congress.gov/v3/member/Q000023?format=json"}], "subjects": {"count": 40, "url": "https://api.congress.gov/v3/bill/117/hr/151/subjects?format=json"}, "summaries": {"count": 1, "url": "https://api.congress.gov/v3/bill/117/hr/151/summaries?format=json"}, "textVersions": {"count": 1, "url": "https://api.congress.gov/v3/bill/117/hr/151/text?format=json"}, "title": "Preventing Future Pandemics Act of 2021", "titles": {"count": 3, "url": "https://api.congress.gov/v3/bill/117/hr/151/titles?format=json"}, "type": "HR", "updateDate": "2024-04-17T23:44:53Z", "updateDateIncludingText": "2024-04-17T23:44:53Z"}