{"actions": {"count": 3, "url": "https://api.congress.gov/v3/bill/117/hr/305/actions?format=json"}, "committees": {"count": 1, "url": "https://api.congress.gov/v3/bill/117/hr/305/committees?format=json"}, "congress": 117, "constitutionalAuthorityStatementText": "<pre>\n[Congressional Record Volume 167, Number 8 (Wednesday, January 13, 2021)]\n[House]\nFrom the Congressional Record Online through the Government Publishing Office [<a href=\"https://www.gpo.gov\">www.gpo.gov</a>]\nBy Mr. CRIST:\nH.R. 305.\nCongress has the power to enact this legislation pursuant\nto the following:\nThe constitutional authority of Congress to enact this\nlegislation is provided by Article I, Section 8 of the United\nStates Constitution.\n[Page H194]\n</pre>", "cosponsors": {"count": 176, "countIncludingWithdrawnCosponsors": 176, "url": "https://api.congress.gov/v3/bill/117/hr/305/cosponsors?format=json"}, "introducedDate": "2021-01-13", "latestAction": {"actionDate": "2021-01-13", "text": "Referred to the House Committee on Financial Services."}, "number": "305", "originChamber": "House", "originChamberCode": "H", "policyArea": {"name": "Congress"}, "relatedBills": {"count": 1, "url": "https://api.congress.gov/v3/bill/117/hr/305/relatedbills?format=json"}, "sponsors": [{"bioguideId": "C001111", "district": 13, "firstName": "Charlie", "fullName": "Rep. Crist, Charlie [D-FL-13]", "isByRequest": "N", "lastName": "Crist", "party": "D", "state": "FL", "url": "https://api.congress.gov/v3/member/C001111?format=json"}], "subjects": {"count": 14, "url": "https://api.congress.gov/v3/bill/117/hr/305/subjects?format=json"}, "summaries": {"count": 1, "url": "https://api.congress.gov/v3/bill/117/hr/305/summaries?format=json"}, "textVersions": {"count": 1, "url": "https://api.congress.gov/v3/bill/117/hr/305/text?format=json"}, "title": "Officer Eugene Goodman Congressional Gold Medal Act", "titles": {"count": 3, "url": "https://api.congress.gov/v3/bill/117/hr/305/titles?format=json"}, "type": "HR", "updateDate": "2024-02-06T19:38:08Z", "updateDateIncludingText": "2024-02-06T19:38:08Z"}