{"actions": {"count": 4, "url": "https://api.congress.gov/v3/bill/117/hr/653/actions?format=json"}, "committees": {"count": 1, "url": "https://api.congress.gov/v3/bill/117/hr/653/committees?format=json"}, "congress": 117, "cosponsors": {"count": 47, "countIncludingWithdrawnCosponsors": 47, "url": "https://api.congress.gov/v3/bill/117/hr/653/cosponsors?format=json"}, "introducedDate": "2021-02-01", "latestAction": {"actionDate": "2021-02-23", "text": "Referred to the Subcommittee on Energy and Mineral Resources."}, "number": "653", "originChamber": "House", "originChamberCode": "H", "policyArea": {"name": "Energy"}, "relatedBills": {"count": 1, "url": "https://api.congress.gov/v3/bill/117/hr/653/relatedbills?format=json"}, "sponsors": [{"bioguideId": "H001068", "district": 2, "firstName": "Jared", "fullName": "Rep. Huffman, Jared [D-CA-2]", "isByRequest": "N", "lastName": "Huffman", "party": "D", "state": "CA", "url": "https://api.congress.gov/v3/member/H001068?format=json"}], "subjects": {"count": 8, "url": "https://api.congress.gov/v3/bill/117/hr/653/subjects?format=json"}, "summaries": {"count": 1, "url": "https://api.congress.gov/v3/bill/117/hr/653/summaries?format=json"}, "textVersions": {"count": 1, "url": "https://api.congress.gov/v3/bill/117/hr/653/text?format=json"}, "title": "West Coast Ocean Protection Act of 2021", "titles": {"count": 3, "url": "https://api.congress.gov/v3/bill/117/hr/653/titles?format=json"}, "type": "HR", "updateDate": "2024-02-07T13:32:55Z", "updateDateIncludingText": "2024-02-07T13:32:55Z"}