{"actions": {"count": 31, "url": "https://api.congress.gov/v3/bill/117/hr/1448/actions?format=json"}, "cboCostEstimates": [{"description": "As passed by the House of Representatives on May 12, 2021\n", "pubDate": "2021-06-11T20:00:00Z", "title": "H.R. 1448, Puppies Assisting Wounded Servicemembers for Veterans Therapy Act", "url": "https://www.cbo.gov/publication/57282"}], "committeeReports": [{"citation": "H. Rept. 117-31", "url": "https://api.congress.gov/v3/committee-report/117/HRPT/31?format=json"}], "committees": {"count": 2, "url": "https://api.congress.gov/v3/bill/117/hr/1448/committees?format=json"}, "congress": 117, "constitutionalAuthorityStatementText": "<pre>\n[Congressional Record Volume 167, Number 38 (Monday, March 1, 2021)]\n[House]\n[Pages H882-H883]\nFrom the Congressional Record Online through the Government Publishing Office [<a href=\"https://www.gpo.gov\">www.gpo.gov</a>]\nBy Mr. STIVERS:\nH.R. 1448.\n[[Page H883]]\nCongress has the power to enact this legislation pursuant\nto the following:\nArticle I, Section 8, Clause 13\nThe Congress shall have Power to provide and maintain a\nNavy.\nArticle I, Section 8, Clause 12\nTo raise and support Armies, but no Appropriation of Money\nto that Use shall be for a longer Term than two Years\nArticle I, Section 8, Clause 14\nTo make Rules for the Government and Regulation of the land\nand naval Forces.\n</pre>", "cosponsors": {"count": 317, "countIncludingWithdrawnCosponsors": 317, "url": "https://api.congress.gov/v3/bill/117/hr/1448/cosponsors?format=json"}, "introducedDate": "2021-03-01", "latestAction": {"actionDate": "2021-08-25", "text": "Became Public Law No: 117-37."}, "laws": [{"number": "117-37", "type": "Public Law"}], "number": "1448", "originChamber": "House", "originChamberCode": "H", "policyArea": {"name": "Armed Forces and National Security"}, "relatedBills": {"count": 2, "url": "https://api.congress.gov/v3/bill/117/hr/1448/relatedbills?format=json"}, "sponsors": [{"bioguideId": "S001187", "district": 15, "firstName": "Steve", "fullName": "Rep. Stivers, Steve [R-OH-15]", "isByRequest": "N", "lastName": "Stivers", "party": "R", "state": "OH", "url": "https://api.congress.gov/v3/member/S001187?format=json"}], "subjects": {"count": 13, "url": "https://api.congress.gov/v3/bill/117/hr/1448/subjects?format=json"}, "summaries": {"count": 4, "url": "https://api.congress.gov/v3/bill/117/hr/1448/summaries?format=json"}, "textVersions": {"count": 6, "url": "https://api.congress.gov/v3/bill/117/hr/1448/text?format=json"}, "title": "PAWS for Veterans Therapy Act", "titles": {"count": 13, "url": "https://api.congress.gov/v3/bill/117/hr/1448/titles?format=json"}, "type": "HR", "updateDate": "2024-04-17T23:44:31Z", "updateDateIncludingText": "2024-04-17T23:44:31Z"}