{"actions": {"count": 3, "url": "https://api.congress.gov/v3/bill/117/hr/1605/actions?format=json"}, "committees": {"count": 1, "url": "https://api.congress.gov/v3/bill/117/hr/1605/committees?format=json"}, "congress": 117, "constitutionalAuthorityStatementText": "<pre>\n[Congressional Record Volume 167, Number 43 (Monday, March 8, 2021)]\n[House]\nFrom the Congressional Record Online through the Government Publishing Office [<a href=\"https://www.gpo.gov\">www.gpo.gov</a>]\nBy Mr. COMER:\nH.R. 1605.\nCongress has the power to enact this legislation pursuant\nto the following:\nArticle I, Section 1, Clause 1; Article 1, Section 8,\nClause 18; and Article 1, Section 9, Clause 7 of the United\nStates Constitution.\n[Page H1120]\n</pre>", "cosponsors": {"count": 3, "countIncludingWithdrawnCosponsors": 3, "url": "https://api.congress.gov/v3/bill/117/hr/1605/cosponsors?format=json"}, "introducedDate": "2021-03-08", "latestAction": {"actionDate": "2021-03-08", "text": "Referred to the House Committee on Oversight and Reform."}, "number": "1605", "originChamber": "House", "originChamberCode": "H", "policyArea": {"name": "Government Operations and Politics"}, "relatedBills": {"count": 1, "url": "https://api.congress.gov/v3/bill/117/hr/1605/relatedbills?format=json"}, "sponsors": [{"bioguideId": "C001108", "district": 1, "firstName": "James", "fullName": "Rep. Comer, James [R-KY-1]", "isByRequest": "N", "lastName": "Comer", "party": "R", "state": "KY", "url": "https://api.congress.gov/v3/member/C001108?format=json"}], "subjects": {"count": 3, "url": "https://api.congress.gov/v3/bill/117/hr/1605/subjects?format=json"}, "summaries": {"count": 1, "url": "https://api.congress.gov/v3/bill/117/hr/1605/summaries?format=json"}, "textVersions": {"count": 1, "url": "https://api.congress.gov/v3/bill/117/hr/1605/text?format=json"}, "title": "GOOD Act", "titles": {"count": 4, "url": "https://api.congress.gov/v3/bill/117/hr/1605/titles?format=json"}, "type": "HR", "updateDate": "2024-02-07T13:33:49Z", "updateDateIncludingText": "2024-02-07T13:33:49Z"}