{"actions": {"count": 4, "url": "https://api.congress.gov/v3/bill/117/hr/2081/actions?format=json"}, "committees": {"count": 1, "url": "https://api.congress.gov/v3/bill/117/hr/2081/committees?format=json"}, "congress": 117, "constitutionalAuthorityStatementText": "<pre>\n[Congressional Record Volume 167, Number 52 (Friday, March 19, 2021)]\n[House]\nFrom the Congressional Record Online through the Government Publishing Office [<a href=\"https://www.gpo.gov\">www.gpo.gov</a>]\nBy Mrs. BOEBERT:\nH.R. 2081.\nCongress has the power to enact this legislation pursuant\nto the following:\nArticle IV, Section 3, Clause 2 (the Property Clause).\nUnder this clause, Congress has the power to dispose of and\nmake all needful rules and regulations respecting the\nterritory or other property belonging to the United States.\nBy virtue of this enumerated power, Congress has governing\nauthority over the lands, territories, or other property of\nthe United States--and with this authority Congress is vested\nwith the power to all owners in fee, the ability to sell,\nlease, dispose, exchange, convey, or simply preserve land.\nArticle 1, Section 8, clause 18 (the Necessary and Proper\nClause). Under this clause, Congress has the power to make\nall Laws which shall be necessary and proper for carrying\ninto Execution the foregoing Powers, and all other Powers\nvested by this Constitution in the Government of the United\nStates, or in any Department or Officer thereof.\n[Page H1612]\n</pre>", "cosponsors": {"count": 10, "countIncludingWithdrawnCosponsors": 10, "url": "https://api.congress.gov/v3/bill/117/hr/2081/cosponsors?format=json"}, "introducedDate": "2021-03-19", "latestAction": {"actionDate": "2021-05-21", "text": "Referred to the Subcommittee on National Parks, Forests, and Public Lands."}, "number": "2081", "originChamber": "House", "originChamberCode": "H", "policyArea": {"name": "Public Lands and Natural Resources"}, "sponsors": [{"bioguideId": "B000825", "district": 3, "firstName": "Lauren", "fullName": "Rep. Boebert, Lauren [R-CO-3]", "isByRequest": "N", "lastName": "Boebert", "party": "R", "state": "CO", "url": "https://api.congress.gov/v3/member/B000825?format=json"}], "subjects": {"count": 22, "url": "https://api.congress.gov/v3/bill/117/hr/2081/subjects?format=json"}, "summaries": {"count": 1, "url": "https://api.congress.gov/v3/bill/117/hr/2081/summaries?format=json"}, "textVersions": {"count": 1, "url": "https://api.congress.gov/v3/bill/117/hr/2081/text?format=json"}, "title": "LOCAL Act", "titles": {"count": 4, "url": "https://api.congress.gov/v3/bill/117/hr/2081/titles?format=json"}, "type": "HR", "updateDate": "2024-02-07T13:32:55Z", "updateDateIncludingText": "2024-02-07T13:32:55Z"}