{"actions": {"count": 3, "url": "https://api.congress.gov/v3/bill/117/hr/2460/actions?format=json"}, "committees": {"count": 1, "url": "https://api.congress.gov/v3/bill/117/hr/2460/committees?format=json"}, "congress": 117, "constitutionalAuthorityStatementText": "<pre>\n[Congressional Record Volume 167, Number 63 (Tuesday, April 13, 2021)]\n[House]\nFrom the Congressional Record Online through the Government Publishing Office [<a href=\"https://www.gpo.gov\">www.gpo.gov</a>]\nBy Mr. PRICE of North Carolina:\nH.R. 2460.\nCongress has the power to enact this legislation pursuant\nto the following:\nAs described in Article 1, Section 1, ``all legislative\npowers herein granted shall be vested in a Congress of the\nUnited States, which shall consist of a Senate and House of\nRepresentatives.''\nArticle I, Section 8, Clause 1 of the Constitution provides\nCongress with the authority to ``provide for the common\nDefense and general Welfare'' of Americans.\nIn the Department of Education Organization Act (P.L. 96-\n88), Congress declared that ``the establishment of a\nDepartment of Education is in the public interest, will\npromote the general welfare of the United States, will help\nensure that education issues receive proper treatment at the\nFederal level, and will enable the Federal Government to\ncoordinate its education activities more effectively.'' The\nDepartment of Education's mission is to ``promote student\nachievement and preparation for global competitiveness by\nfostering educational excellence and ensuring equal access.''\n[Page H1737]\n</pre>", "cosponsors": {"count": 25, "countIncludingWithdrawnCosponsors": 26, "url": "https://api.congress.gov/v3/bill/117/hr/2460/cosponsors?format=json"}, "introducedDate": "2021-04-13", "latestAction": {"actionDate": "2021-04-13", "text": "Referred to the House Committee on Education and Labor."}, "number": "2460", "originChamber": "House", "originChamberCode": "H", "policyArea": {"name": "Education"}, "relatedBills": {"count": 1, "url": "https://api.congress.gov/v3/bill/117/hr/2460/relatedbills?format=json"}, "sponsors": [{"bioguideId": "P000523", "district": 4, "firstName": "DAVID", "fullName": "Rep. Price, David E. [D-NC-4]", "isByRequest": "N", "lastName": "PRICE", "middleName": "E.", "party": "D", "state": "NC", "url": "https://api.congress.gov/v3/member/P000523?format=json"}], "subjects": {"count": 7, "url": "https://api.congress.gov/v3/bill/117/hr/2460/subjects?format=json"}, "summaries": {"count": 1, "url": "https://api.congress.gov/v3/bill/117/hr/2460/summaries?format=json"}, "textVersions": {"count": 1, "url": "https://api.congress.gov/v3/bill/117/hr/2460/text?format=json"}, "title": "Joint Consolidation Loan Separation Act", "titles": {"count": 3, "url": "https://api.congress.gov/v3/bill/117/hr/2460/titles?format=json"}, "type": "HR", "updateDate": "2024-02-06T18:49:25Z", "updateDateIncludingText": "2024-02-06T18:49:25Z"}