{"actions": {"count": 4, "url": "https://api.congress.gov/v3/bill/117/hr/2531/actions?format=json"}, "committees": {"count": 1, "url": "https://api.congress.gov/v3/bill/117/hr/2531/committees?format=json"}, "congress": 117, "constitutionalAuthorityStatementText": "<pre>\n[Congressional Record Volume 167, Number 64 (Wednesday, April 14, 2021)]\n[House]\nFrom the Congressional Record Online through the Government Publishing Office [<a href=\"https://www.gpo.gov\">www.gpo.gov</a>]\nBy Mr. PANETTA:\nH.R. 2531.\nCongress has the power to enact this legislation pursuant\nto the following:\nArticle 1, Section 8, Clause 18\n[Page H1791]\n</pre>", "cosponsors": {"count": 3, "countIncludingWithdrawnCosponsors": 3, "url": "https://api.congress.gov/v3/bill/117/hr/2531/cosponsors?format=json"}, "introducedDate": "2021-04-14", "latestAction": {"actionDate": "2021-07-14", "text": "Referred to the Subcommittee on Economic Opportunity."}, "number": "2531", "originChamber": "House", "originChamberCode": "H", "policyArea": {"name": "Armed Forces and National Security"}, "sponsors": [{"bioguideId": "P000613", "district": 20, "firstName": "Jimmy", "fullName": "Rep. Panetta, Jimmy [D-CA-20]", "isByRequest": "N", "lastName": "Panetta", "party": "D", "state": "CA", "url": "https://api.congress.gov/v3/member/P000613?format=json"}], "subjects": {"count": 5, "url": "https://api.congress.gov/v3/bill/117/hr/2531/subjects?format=json"}, "summaries": {"count": 1, "url": "https://api.congress.gov/v3/bill/117/hr/2531/summaries?format=json"}, "textVersions": {"count": 1, "url": "https://api.congress.gov/v3/bill/117/hr/2531/text?format=json"}, "title": "Vets ETA", "titles": {"count": 4, "url": "https://api.congress.gov/v3/bill/117/hr/2531/titles?format=json"}, "type": "HR", "updateDate": "2024-02-07T16:12:44Z", "updateDateIncludingText": "2024-02-07T16:12:44Z"}