{"actions": {"count": 11, "url": "https://api.congress.gov/v3/bill/117/hr/3128/actions?format=json"}, "committeeReports": [{"citation": "H. Rept. 117-635", "url": "https://api.congress.gov/v3/committee-report/117/HRPT/635?format=json"}], "committees": {"count": 1, "url": "https://api.congress.gov/v3/bill/117/hr/3128/committees?format=json"}, "congress": 117, "constitutionalAuthorityStatementText": "<pre>\n[Congressional Record Volume 167, Number 81 (Tuesday, May 11, 2021)]\n[House]\nFrom the Congressional Record Online through the Government Publishing Office [<a href=\"https://www.gpo.gov\">www.gpo.gov</a>]\nBy Mr. YOUNG:\nH.R. 3128.\nCongress has the power to enact this legislation pursuant\nto the following:\nArticle I, Section 8, Clause 18\n[Page H2196]\n</pre>", "cosponsors": {"count": 1, "countIncludingWithdrawnCosponsors": 1, "url": "https://api.congress.gov/v3/bill/117/hr/3128/cosponsors?format=json"}, "introducedDate": "2021-05-11", "latestAction": {"actionDate": "2022-12-14", "text": "Placed on the Union Calendar, Calendar No. 458."}, "number": "3128", "originChamber": "House", "originChamberCode": "H", "policyArea": {"name": "Public Lands and Natural Resources"}, "relatedBills": {"count": 3, "url": "https://api.congress.gov/v3/bill/117/hr/3128/relatedbills?format=json"}, "sponsors": [{"bioguideId": "Y000033", "firstName": "DON", "fullName": "Rep. Young, Don [R-AK-At Large]", "isByRequest": "N", "lastName": "YOUNG", "middleName": "E.", "party": "R", "state": "AK", "url": "https://api.congress.gov/v3/member/Y000033?format=json"}], "subjects": {"count": 9, "url": "https://api.congress.gov/v3/bill/117/hr/3128/subjects?format=json"}, "summaries": {"count": 2, "url": "https://api.congress.gov/v3/bill/117/hr/3128/summaries?format=json"}, "textVersions": {"count": 2, "url": "https://api.congress.gov/v3/bill/117/hr/3128/text?format=json"}, "title": "American Fisheries Advisory Committee Act of 2021", "titles": {"count": 4, "url": "https://api.congress.gov/v3/bill/117/hr/3128/titles?format=json"}, "type": "HR", "updateDate": "2024-04-17T23:45:25Z", "updateDateIncludingText": "2024-04-17T23:45:25Z"}