{"actions": {"count": 4, "url": "https://api.congress.gov/v3/bill/117/hr/3250/actions?format=json"}, "committees": {"count": 1, "url": "https://api.congress.gov/v3/bill/117/hr/3250/committees?format=json"}, "congress": 117, "constitutionalAuthorityStatementText": "<pre>\n[Congressional Record Volume 167, Number 84 (Friday, May 14, 2021)]\n[House]\nFrom the Congressional Record Online through the Government Publishing Office [<a href=\"https://www.gpo.gov\">www.gpo.gov</a>]\nBy Mr. HOLLINGSWORTH:\nH.R. 3250.\nCongress has the power to enact this legislation pursuant\nto the following:\nArticle I, Section 8, Clause 18: To make all Laws which\nshall be necessary and proper for carrying into Execution the\nforegoing Powers, and all other Powers vested by this\nConstitution in the Government of the United States, or in\nany Department or Officer thereof.\n[Page H2357]\n</pre>", "cosponsors": {"count": 3, "countIncludingWithdrawnCosponsors": 3, "url": "https://api.congress.gov/v3/bill/117/hr/3250/cosponsors?format=json"}, "introducedDate": "2021-05-14", "latestAction": {"actionDate": "2021-11-09", "text": "Referred to the Subcommittee on Crime, Terrorism, and Homeland Security."}, "number": "3250", "originChamber": "House", "originChamberCode": "H", "policyArea": {"name": "Crime and Law Enforcement"}, "sponsors": [{"bioguideId": "H001074", "district": 9, "firstName": "Trey", "fullName": "Rep. Hollingsworth, Trey [R-IN-9]", "isByRequest": "N", "lastName": "Hollingsworth", "party": "R", "state": "IN", "url": "https://api.congress.gov/v3/member/H001074?format=json"}], "subjects": {"count": 1, "url": "https://api.congress.gov/v3/bill/117/hr/3250/subjects?format=json"}, "summaries": {"count": 1, "url": "https://api.congress.gov/v3/bill/117/hr/3250/summaries?format=json"}, "textVersions": {"count": 1, "url": "https://api.congress.gov/v3/bill/117/hr/3250/text?format=json"}, "title": "POLICE Act of 2021", "titles": {"count": 4, "url": "https://api.congress.gov/v3/bill/117/hr/3250/titles?format=json"}, "type": "HR", "updateDate": "2024-04-17T23:44:08Z", "updateDateIncludingText": "2024-04-17T23:44:08Z"}