{"actions": {"count": 4, "url": "https://api.congress.gov/v3/bill/117/hr/4206/actions?format=json"}, "committees": {"count": 1, "url": "https://api.congress.gov/v3/bill/117/hr/4206/committees?format=json"}, "congress": 117, "constitutionalAuthorityStatementText": "<pre>\n[Congressional Record Volume 167, Number 112 (Monday, June 28, 2021)]\n[House]\nFrom the Congressional Record Online through the Government Publishing Office [<a href=\"https://www.gpo.gov\">www.gpo.gov</a>]\nBy Ms. NORTON:\nH.R. 4206.\nCongress has the power to enact this legislation pursuant\nto the following:\nclause 17 of section 8 of article I of the Constitution.\n[Page H3240]\n</pre>", "introducedDate": "2021-06-28", "latestAction": {"actionDate": "2021-06-28", "text": "Referred to the House Committee on Oversight and Reform."}, "number": "4206", "originChamber": "House", "originChamberCode": "H", "policyArea": {"name": "Crime and Law Enforcement"}, "relatedBills": {"count": 1, "url": "https://api.congress.gov/v3/bill/117/hr/4206/relatedbills?format=json"}, "sponsors": [{"bioguideId": "N000147", "firstName": "ELEANOR", "fullName": "Del. Norton, Eleanor Holmes [D-DC-At Large]", "isByRequest": "N", "lastName": "NORTON", "middleName": "HOLMES", "party": "D", "state": "DC", "url": "https://api.congress.gov/v3/member/N000147?format=json"}], "subjects": {"count": 6, "url": "https://api.congress.gov/v3/bill/117/hr/4206/subjects?format=json"}, "summaries": {"count": 1, "url": "https://api.congress.gov/v3/bill/117/hr/4206/summaries?format=json"}, "textVersions": {"count": 1, "url": "https://api.congress.gov/v3/bill/117/hr/4206/text?format=json"}, "title": "District of Columbia Clemency Home Rule Act", "titles": {"count": 3, "url": "https://api.congress.gov/v3/bill/117/hr/4206/titles?format=json"}, "type": "HR", "updateDate": "2024-02-07T13:33:49Z", "updateDateIncludingText": "2024-02-07T13:33:49Z"}