{"actions": {"count": 27, "url": "https://api.congress.gov/v3/bill/117/hr/4250/actions?format=json"}, "cboCostEstimates": [{"description": "As ordered reported by the House Committee on Foreign Affairs on July 29, 2021.\n", "pubDate": "2021-08-24T16:26:00Z", "title": "H.R. 4250, War Crimes Rewards Expansion Act", "url": "https://www.cbo.gov/publication/57439"}, {"description": "As reported by the Senate Committee on Foreign Relations on June 14, 2022\n", "pubDate": "2022-06-27T20:00:00Z", "title": "H.R. 4250, War Crimes Rewards Expansion Act", "url": "https://www.cbo.gov/publication/58240"}], "committees": {"count": 2, "url": "https://api.congress.gov/v3/bill/117/hr/4250/committees?format=json"}, "congress": 117, "constitutionalAuthorityStatementText": "<pre>\n[Congressional Record Volume 167, Number 114 (Wednesday, June 30, 2021)]\n[House]\nFrom the Congressional Record Online through the Government Publishing Office [<a href=\"https://www.gpo.gov\">www.gpo.gov</a>]\nBy Ms. FOXX:\nH.R. 4250.\nCongress has the power to enact this legislation pursuant\nto the following:\nArticle 1, Section 8, Clause 1 grants Congress the power to\n``To define and punish Piracies and Felonies committed on the\nhigh Seas, and Offences against the Law of Nations;''\n[Page H3580]\n</pre>", "cosponsors": {"count": 8, "countIncludingWithdrawnCosponsors": 8, "url": "https://api.congress.gov/v3/bill/117/hr/4250/cosponsors?format=json"}, "introducedDate": "2021-06-30", "latestAction": {"actionDate": "2022-12-27", "text": "Became Public Law No: 117-273."}, "laws": [{"number": "117-273", "type": "Public Law"}], "number": "4250", "originChamber": "House", "originChamberCode": "H", "policyArea": {"name": "International Affairs"}, "sponsors": [{"bioguideId": "F000450", "district": 5, "firstName": "Virginia", "fullName": "Rep. Foxx, Virginia [R-NC-5]", "isByRequest": "N", "lastName": "Foxx", "party": "R", "state": "NC", "url": "https://api.congress.gov/v3/member/F000450?format=json"}], "subjects": {"count": 4, "url": "https://api.congress.gov/v3/bill/117/hr/4250/subjects?format=json"}, "summaries": {"count": 5, "url": "https://api.congress.gov/v3/bill/117/hr/4250/summaries?format=json"}, "textVersions": {"count": 6, "url": "https://api.congress.gov/v3/bill/117/hr/4250/text?format=json"}, "title": "War Crimes Rewards Expansion Act", "titles": {"count": 8, "url": "https://api.congress.gov/v3/bill/117/hr/4250/titles?format=json"}, "type": "HR", "updateDate": "2024-04-17T23:44:51Z", "updateDateIncludingText": "2024-04-17T23:44:51Z"}