{"actions": {"count": 10, "url": "https://api.congress.gov/v3/bill/117/hr/4252/actions?format=json"}, "committeeReports": [{"citation": "H. Rept. 117-172", "url": "https://api.congress.gov/v3/committee-report/117/HRPT/172?format=json"}], "committees": {"count": 1, "url": "https://api.congress.gov/v3/bill/117/hr/4252/committees?format=json"}, "congress": 117, "constitutionalAuthorityStatementText": "<pre>\n[Congressional Record Volume 167, Number 114 (Wednesday, June 30, 2021)]\n[House]\nFrom the Congressional Record Online through the Government Publishing Office [<a href=\"https://www.gpo.gov\">www.gpo.gov</a>]\nBy Mr. DAVID SCOTT of Georgia:\nH.R. 4252.\nCongress has the power to enact this legislation pursuant\nto the following:\nU.S. Const. art. I, Sec. 8, cl. 1 and cl. 18\n[Page H3580]\n</pre>", "cosponsors": {"count": 12, "countIncludingWithdrawnCosponsors": 12, "url": "https://api.congress.gov/v3/bill/117/hr/4252/cosponsors?format=json"}, "introducedDate": "2021-06-30", "latestAction": {"actionDate": "2021-11-03", "text": "Placed on the Union Calendar, Calendar No. 126."}, "number": "4252", "originChamber": "House", "originChamberCode": "H", "policyArea": {"name": "Agriculture and Food"}, "sponsors": [{"bioguideId": "S001157", "district": 13, "firstName": "David", "fullName": "Rep. Scott, David [D-GA-13]", "isByRequest": "N", "lastName": "Scott", "party": "D", "state": "GA", "url": "https://api.congress.gov/v3/member/S001157?format=json"}], "subjects": {"count": 5, "url": "https://api.congress.gov/v3/bill/117/hr/4252/subjects?format=json"}, "summaries": {"count": 2, "url": "https://api.congress.gov/v3/bill/117/hr/4252/summaries?format=json"}, "textVersions": {"count": 2, "url": "https://api.congress.gov/v3/bill/117/hr/4252/text?format=json"}, "title": "To provide additional funding for scholarships for students at 1890 institutions.", "titles": {"count": 2, "url": "https://api.congress.gov/v3/bill/117/hr/4252/titles?format=json"}, "type": "HR", "updateDate": "2024-04-17T23:45:19Z", "updateDateIncludingText": "2024-04-17T23:45:19Z"}