{"actions": {"count": 4, "url": "https://api.congress.gov/v3/bill/117/hr/5131/actions?format=json"}, "committees": {"count": 1, "url": "https://api.congress.gov/v3/bill/117/hr/5131/committees?format=json"}, "congress": 117, "constitutionalAuthorityStatementText": "<pre>\n[Congressional Record Volume 167, Number 152 (Tuesday, August 31, 2021)]\n[House]\nFrom the Congressional Record Online through the Government Publishing Office [<a href=\"https://www.gpo.gov\">www.gpo.gov</a>]\nBy Mr. CARDENAS:\nH.R. 5131.\nCongress has the power to enact this legislation pursuant\nto the following:\nArticle 1 Section 8 of the U.S. Constitution\n[Page H4501]\n</pre>", "cosponsors": {"count": 19, "countIncludingWithdrawnCosponsors": 19, "url": "https://api.congress.gov/v3/bill/117/hr/5131/cosponsors?format=json"}, "introducedDate": "2021-08-31", "latestAction": {"actionDate": "2021-09-01", "text": "Referred to the Subcommittee on Health."}, "number": "5131", "originChamber": "House", "originChamberCode": "H", "policyArea": {"name": "Health"}, "relatedBills": {"count": 1, "url": "https://api.congress.gov/v3/bill/117/hr/5131/relatedbills?format=json"}, "sponsors": [{"bioguideId": "C001097", "district": 29, "firstName": "Tony", "fullName": "Rep. C\u00e1rdenas, Tony [D-CA-29]", "isByRequest": "N", "lastName": "C\u00e1rdenas", "party": "D", "state": "CA", "url": "https://api.congress.gov/v3/member/C001097?format=json"}], "subjects": {"count": 1, "url": "https://api.congress.gov/v3/bill/117/hr/5131/subjects?format=json"}, "summaries": {"count": 1, "url": "https://api.congress.gov/v3/bill/117/hr/5131/summaries?format=json"}, "textVersions": {"count": 1, "url": "https://api.congress.gov/v3/bill/117/hr/5131/text?format=json"}, "title": "Pediatric Access to Critical Healthcare Act", "titles": {"count": 3, "url": "https://api.congress.gov/v3/bill/117/hr/5131/titles?format=json"}, "type": "HR", "updateDate": "2024-02-05T14:30:09Z", "updateDateIncludingText": "2024-02-05T14:30:09Z"}