{"actions": {"count": 25, "url": "https://api.congress.gov/v3/bill/117/hr/5221/actions?format=json"}, "cboCostEstimates": [{"description": "As ordered reported by the House Committee on Natural Resources on October 13, 2021\n", "pubDate": "2021-10-21T20:14:00Z", "title": "H.R. 5221, Urban Indian Health Confer Act", "url": "https://www.cbo.gov/publication/57565"}], "committeeReports": [{"citation": "H. Rept. 117-168", "url": "https://api.congress.gov/v3/committee-report/117/HRPT/168?format=json"}], "committees": {"count": 3, "url": "https://api.congress.gov/v3/bill/117/hr/5221/committees?format=json"}, "congress": 117, "constitutionalAuthorityStatementText": "<pre>\n[Congressional Record Volume 167, Number 156 (Friday, September 10, 2021)]\n[House]\nFrom the Congressional Record Online through the Government Publishing Office [<a href=\"https://www.gpo.gov\">www.gpo.gov</a>]\nBy Mr. GRIJALVA:\nH.R. 5221.\nCongress has the power to enact this legislation pursuant\nto the following:\nU.S. Constitution Article 1 Sections 1 and 8\n[Page H4517]\n</pre>", "cosponsors": {"count": 19, "countIncludingWithdrawnCosponsors": 19, "url": "https://api.congress.gov/v3/bill/117/hr/5221/cosponsors?format=json"}, "introducedDate": "2021-09-10", "latestAction": {"actionDate": "2022-07-20", "text": "Committee on Indian Affairs. Hearings held. Hearings printed: S.Hrg. 117-530."}, "number": "5221", "originChamber": "House", "originChamberCode": "H", "policyArea": {"name": "Native Americans"}, "relatedBills": {"count": 2, "url": "https://api.congress.gov/v3/bill/117/hr/5221/relatedbills?format=json"}, "sponsors": [{"bioguideId": "G000551", "district": 3, "firstName": "Ra\u00fal", "fullName": "Rep. Grijalva, Ra\u00fal M. [D-AZ-3]", "isByRequest": "N", "lastName": "Grijalva", "middleName": "M.", "party": "D", "state": "AZ", "url": "https://api.congress.gov/v3/member/G000551?format=json"}], "subjects": {"count": 6, "url": "https://api.congress.gov/v3/bill/117/hr/5221/subjects?format=json"}, "summaries": {"count": 3, "url": "https://api.congress.gov/v3/bill/117/hr/5221/summaries?format=json"}, "textVersions": {"count": 4, "url": "https://api.congress.gov/v3/bill/117/hr/5221/text?format=json"}, "title": "Urban Indian Health Confer Act", "titles": {"count": 6, "url": "https://api.congress.gov/v3/bill/117/hr/5221/titles?format=json"}, "type": "HR", "updateDate": "2024-04-17T23:44:57Z", "updateDateIncludingText": "2024-04-17T23:44:57Z"}