{"actions": {"count": 4, "url": "https://api.congress.gov/v3/bill/117/hr/6069/actions?format=json"}, "committees": {"count": 1, "url": "https://api.congress.gov/v3/bill/117/hr/6069/committees?format=json"}, "congress": 117, "constitutionalAuthorityStatementText": "<pre>\n[Congressional Record Volume 167, Number 203 (Tuesday, November 23, 2021)]\n[House]\nFrom the Congressional Record Online through the Government Publishing Office [<a href=\"https://www.gpo.gov\">www.gpo.gov</a>]\nBy Mrs. FISCHBACH:\nH.R. 6069.\nCongress has the power to enact this legislation pursuant\nto the following:\nArticle 1 Section 8\n[Page H6673]\n</pre>", "cosponsors": {"count": 29, "countIncludingWithdrawnCosponsors": 29, "url": "https://api.congress.gov/v3/bill/117/hr/6069/cosponsors?format=json"}, "introducedDate": "2021-11-23", "latestAction": {"actionDate": "2022-02-22", "text": "Referred to the Subcommittee on Asia, the Pacific, Central Asia and Nonproliferation."}, "number": "6069", "originChamber": "House", "originChamberCode": "H", "policyArea": {"name": "International Affairs"}, "sponsors": [{"bioguideId": "F000470", "district": 7, "firstName": "Michelle", "fullName": "Rep. Fischbach, Michelle [R-MN-7]", "isByRequest": "N", "lastName": "Fischbach", "party": "R", "state": "MN", "url": "https://api.congress.gov/v3/member/F000470?format=json"}], "subjects": {"count": 1, "url": "https://api.congress.gov/v3/bill/117/hr/6069/subjects?format=json"}, "summaries": {"count": 1, "url": "https://api.congress.gov/v3/bill/117/hr/6069/summaries?format=json"}, "textVersions": {"count": 1, "url": "https://api.congress.gov/v3/bill/117/hr/6069/text?format=json"}, "title": "Promoting Ties with Taiwan Act", "titles": {"count": 3, "url": "https://api.congress.gov/v3/bill/117/hr/6069/titles?format=json"}, "type": "HR", "updateDate": "2024-02-07T11:38:03Z", "updateDateIncludingText": "2024-02-07T11:38:03Z"}