{"actions": {"count": 5, "url": "https://api.congress.gov/v3/bill/117/hr/6229/actions?format=json"}, "committees": {"count": 1, "url": "https://api.congress.gov/v3/bill/117/hr/6229/committees?format=json"}, "congress": 117, "constitutionalAuthorityStatementText": "<pre>\n[Congressional Record Volume 167, Number 213 (Thursday, December 9, 2021)]\n[House]\nFrom the Congressional Record Online through the Government Publishing Office [<a href=\"https://www.gpo.gov\">www.gpo.gov</a>]\nBy Mr. MAST:\nH.R. 6229.\nCongress has the power to enact this legislation pursuant\nto the following:\nArticle I, Section 8, Clause 18 of the United States\nConstitution\n[Page H7638]\n</pre>", "cosponsors": {"count": 6, "countIncludingWithdrawnCosponsors": 6, "url": "https://api.congress.gov/v3/bill/117/hr/6229/cosponsors?format=json"}, "introducedDate": "2021-12-09", "latestAction": {"actionDate": "2021-12-20", "text": "Referred to the Subcommittee on Water, Oceans, and Wildlife."}, "number": "6229", "originChamber": "House", "originChamberCode": "H", "policyArea": {"name": "Public Lands and Natural Resources"}, "relatedBills": {"count": 1, "url": "https://api.congress.gov/v3/bill/117/hr/6229/relatedbills?format=json"}, "sponsors": [{"bioguideId": "M001199", "district": 18, "firstName": "Brian", "fullName": "Rep. Mast, Brian J. [R-FL-18]", "isByRequest": "N", "lastName": "Mast", "middleName": "J.", "party": "R", "state": "FL", "url": "https://api.congress.gov/v3/member/M001199?format=json"}], "subjects": {"count": 1, "url": "https://api.congress.gov/v3/bill/117/hr/6229/subjects?format=json"}, "summaries": {"count": 1, "url": "https://api.congress.gov/v3/bill/117/hr/6229/summaries?format=json"}, "textVersions": {"count": 1, "url": "https://api.congress.gov/v3/bill/117/hr/6229/text?format=json"}, "title": "Land and Water Conservation Fund Water Amendments Act of 2021", "titles": {"count": 3, "url": "https://api.congress.gov/v3/bill/117/hr/6229/titles?format=json"}, "type": "HR", "updateDate": "2024-03-26T13:06:56Z", "updateDateIncludingText": "2024-03-26T13:06:56Z"}