{"actions": {"count": 3, "url": "https://api.congress.gov/v3/bill/117/hr/6371/actions?format=json"}, "committees": {"count": 1, "url": "https://api.congress.gov/v3/bill/117/hr/6371/committees?format=json"}, "congress": 117, "constitutionalAuthorityStatementText": "<pre>\n[Congressional Record Volume 168, Number 7 (Tuesday, January 11, 2022)]\n[House]\nFrom the Congressional Record Online through the Government Publishing Office [<a href=\"https://www.gpo.gov\">www.gpo.gov</a>]\nBy Mrs. DINGELL:\nH.R. 6371.\nCongress has the power to enact this legislation pursuant\nto the following:\nThe constitutional authority of Congress to enact this\nlegislation is provided by Article I, section 8 of the United\nStates Constitution.\n[Page H43]\n</pre>", "introducedDate": "2022-01-11", "latestAction": {"actionDate": "2022-01-11", "text": "Referred to the House Committee on Education and Labor."}, "number": "6371", "originChamber": "House", "originChamberCode": "H", "policyArea": {"name": "Education"}, "relatedBills": {"count": 1, "url": "https://api.congress.gov/v3/bill/117/hr/6371/relatedbills?format=json"}, "sponsors": [{"bioguideId": "D000624", "district": 12, "firstName": "Debbie", "fullName": "Rep. Dingell, Debbie [D-MI-12]", "isByRequest": "N", "lastName": "Dingell", "party": "D", "state": "MI", "url": "https://api.congress.gov/v3/member/D000624?format=json"}], "subjects": {"count": 1, "url": "https://api.congress.gov/v3/bill/117/hr/6371/subjects?format=json"}, "summaries": {"count": 1, "url": "https://api.congress.gov/v3/bill/117/hr/6371/summaries?format=json"}, "textVersions": {"count": 1, "url": "https://api.congress.gov/v3/bill/117/hr/6371/text?format=json"}, "title": "Safe Equitable Campus Resources and Education Act of 2022", "titles": {"count": 3, "url": "https://api.congress.gov/v3/bill/117/hr/6371/titles?format=json"}, "type": "HR", "updateDate": "2024-02-06T18:49:25Z", "updateDateIncludingText": "2024-02-06T18:49:25Z"}