{"actions": {"count": 7, "url": "https://api.congress.gov/v3/bill/117/hr/6400/actions?format=json"}, "committees": {"count": 3, "url": "https://api.congress.gov/v3/bill/117/hr/6400/committees?format=json"}, "congress": 117, "constitutionalAuthorityStatementText": "<pre>\n[Congressional Record Volume 168, Number 9 (Thursday, January 13, 2022)]\n[House]\nFrom the Congressional Record Online through the Government Publishing Office [<a href=\"https://www.gpo.gov\">www.gpo.gov</a>]\nBy Mr. GRAVES of Missouri:\nH.R. 6400.\nCongress has the power to enact this legislation pursuant\nto the following:\nSection 8 of Article I the United States Constitution.\n[Page H194]\n</pre>", "cosponsors": {"count": 5, "countIncludingWithdrawnCosponsors": 5, "url": "https://api.congress.gov/v3/bill/117/hr/6400/cosponsors?format=json"}, "introducedDate": "2022-01-13", "latestAction": {"actionDate": "2022-01-14", "text": "Referred to the Subcommittee on Health."}, "number": "6400", "originChamber": "House", "originChamberCode": "H", "policyArea": {"name": "Health"}, "relatedBills": {"count": 1, "url": "https://api.congress.gov/v3/bill/117/hr/6400/relatedbills?format=json"}, "sponsors": [{"bioguideId": "G000546", "district": 6, "firstName": "SAM", "fullName": "Rep. Graves, Sam [R-MO-6]", "isByRequest": "N", "lastName": "GRAVES", "party": "R", "state": "MO", "url": "https://api.congress.gov/v3/member/G000546?format=json"}], "subjects": {"count": 24, "url": "https://api.congress.gov/v3/bill/117/hr/6400/subjects?format=json"}, "summaries": {"count": 1, "url": "https://api.congress.gov/v3/bill/117/hr/6400/summaries?format=json"}, "textVersions": {"count": 1, "url": "https://api.congress.gov/v3/bill/117/hr/6400/text?format=json"}, "title": "Save America\u2019s Rural Hospitals Act", "titles": {"count": 3, "url": "https://api.congress.gov/v3/bill/117/hr/6400/titles?format=json"}, "type": "HR", "updateDate": "2024-04-17T23:44:26Z", "updateDateIncludingText": "2024-04-17T23:44:26Z"}