{"actions": {"count": 7, "url": "https://api.congress.gov/v3/bill/117/hr/6837/actions?format=json"}, "cboCostEstimates": [{"description": "As ordered reported by the House Committee on Homeland Security on March 2, 2022\n", "pubDate": "2022-03-22T15:06:00Z", "title": "H.R. 6837, No TikTok on Department of Homeland Security Devices Act", "url": "https://www.cbo.gov/publication/57939"}], "committees": {"count": 1, "url": "https://api.congress.gov/v3/bill/117/hr/6837/committees?format=json"}, "congress": 117, "constitutionalAuthorityStatementText": "<pre>\n[Congressional Record Volume 168, Number 35 (Friday, February 25, 2022)]\n[House]\nFrom the Congressional Record Online through the Government Publishing Office [<a href=\"https://www.gpo.gov\">www.gpo.gov</a>]\nBy Mr. GUEST:\nH.R. 6837.\nCongress has the power to enact this legislation pursuant\nto the following:\nArticle I, Section 8\n[Page H1148]\n</pre>", "cosponsors": {"count": 1, "countIncludingWithdrawnCosponsors": 1, "url": "https://api.congress.gov/v3/bill/117/hr/6837/cosponsors?format=json"}, "introducedDate": "2022-02-25", "latestAction": {"actionDate": "2022-03-02", "text": "Subcommittee on Oversight, Management, and Accountability Discharged."}, "number": "6837", "originChamber": "House", "originChamberCode": "H", "policyArea": {"name": "Government Operations and Politics"}, "sponsors": [{"bioguideId": "G000591", "district": 3, "firstName": "Michael", "fullName": "Rep. Guest, Michael [R-MS-3]", "isByRequest": "N", "lastName": "Guest", "party": "R", "state": "MS", "url": "https://api.congress.gov/v3/member/G000591?format=json"}], "subjects": {"count": 6, "url": "https://api.congress.gov/v3/bill/117/hr/6837/subjects?format=json"}, "summaries": {"count": 1, "url": "https://api.congress.gov/v3/bill/117/hr/6837/summaries?format=json"}, "textVersions": {"count": 1, "url": "https://api.congress.gov/v3/bill/117/hr/6837/text?format=json"}, "title": "No TikTok on Department of Homeland Security Devices Act", "titles": {"count": 3, "url": "https://api.congress.gov/v3/bill/117/hr/6837/titles?format=json"}, "type": "HR", "updateDate": "2024-04-17T23:44:40Z", "updateDateIncludingText": "2024-04-17T23:44:40Z"}