{"actions": {"count": 3, "url": "https://api.congress.gov/v3/bill/117/hr/7994/actions?format=json"}, "committees": {"count": 1, "url": "https://api.congress.gov/v3/bill/117/hr/7994/committees?format=json"}, "congress": 117, "constitutionalAuthorityStatementText": "<pre>\n[Congressional Record Volume 168, Number 99 (Thursday, June 9, 2022)]\n[House]\nFrom the Congressional Record Online through the Government Publishing Office [<a href=\"https://www.gpo.gov\">www.gpo.gov</a>]\nBy Mr. WILSON of South Carolina:\nH.R. 7994.\nCongress has the power to enact this legislation pursuant\nto the following:\nArticle I Section 8 of the US Constitution.\n[Page H5446]\n</pre>", "introducedDate": "2022-06-09", "latestAction": {"actionDate": "2022-06-09", "text": "Referred to the House Committee on Armed Services."}, "number": "7994", "originChamber": "House", "originChamberCode": "H", "policyArea": {"name": "Armed Forces and National Security"}, "sponsors": [{"bioguideId": "W000795", "district": 2, "firstName": "Joe", "fullName": "Rep. Wilson, Joe [R-SC-2]", "isByRequest": "N", "lastName": "Wilson", "party": "R", "state": "SC", "url": "https://api.congress.gov/v3/member/W000795?format=json"}], "subjects": {"count": 1, "url": "https://api.congress.gov/v3/bill/117/hr/7994/subjects?format=json"}, "summaries": {"count": 1, "url": "https://api.congress.gov/v3/bill/117/hr/7994/summaries?format=json"}, "textVersions": {"count": 1, "url": "https://api.congress.gov/v3/bill/117/hr/7994/text?format=json"}, "title": "PERFORMS Act", "titles": {"count": 4, "url": "https://api.congress.gov/v3/bill/117/hr/7994/titles?format=json"}, "type": "HR", "updateDate": "2023-08-09T19:15:25Z", "updateDateIncludingText": "2023-08-09T19:15:25Z"}