{"actions": {"count": 5, "url": "https://api.congress.gov/v3/bill/117/hr/8358/actions?format=json"}, "committees": {"count": 1, "url": "https://api.congress.gov/v3/bill/117/hr/8358/committees?format=json"}, "congress": 117, "constitutionalAuthorityStatementText": "<pre>\n[Congressional Record Volume 168, Number 115 (Wednesday, July 13, 2022)]\n[House]\nFrom the Congressional Record Online through the Government Publishing Office [<a href=\"https://www.gpo.gov\">www.gpo.gov</a>]\nBy Ms. DELAURO:\nH.R. 8358.\nCongress has the power to enact this legislation pursuant\nto the following:\nArticle I, Section 8, clause 3 provides Congress with the\npower to ``regulate commerce with foreign nations, and among\nthe several states, and with the Indian tribes.''\n[Page H6336]\n</pre>", "cosponsors": {"count": 5, "countIncludingWithdrawnCosponsors": 5, "url": "https://api.congress.gov/v3/bill/117/hr/8358/cosponsors?format=json"}, "introducedDate": "2022-07-13", "latestAction": {"actionDate": "2022-07-13", "text": "Referred to the House Committee on Energy and Commerce."}, "number": "8358", "originChamber": "House", "originChamberCode": "H", "policyArea": {"name": "Health"}, "relatedBills": {"count": 1, "url": "https://api.congress.gov/v3/bill/117/hr/8358/relatedbills?format=json"}, "sponsors": [{"bioguideId": "D000216", "district": 3, "firstName": "ROSA", "fullName": "Rep. DeLauro, Rosa L. [D-CT-3]", "isByRequest": "N", "lastName": "DELAURO", "party": "D", "state": "CT", "url": "https://api.congress.gov/v3/member/D000216?format=json"}], "subjects": {"count": 1, "url": "https://api.congress.gov/v3/bill/117/hr/8358/subjects?format=json"}, "summaries": {"count": 1, "url": "https://api.congress.gov/v3/bill/117/hr/8358/summaries?format=json"}, "textVersions": {"count": 1, "url": "https://api.congress.gov/v3/bill/117/hr/8358/text?format=json"}, "title": "Food Safety Administration Act of 2022", "titles": {"count": 3, "url": "https://api.congress.gov/v3/bill/117/hr/8358/titles?format=json"}, "type": "HR", "updateDate": "2024-02-05T14:30:09Z", "updateDateIncludingText": "2024-02-05T14:30:09Z"}