{"actions": {"count": 3, "url": "https://api.congress.gov/v3/bill/117/hr/8690/actions?format=json"}, "committees": {"count": 1, "url": "https://api.congress.gov/v3/bill/117/hr/8690/committees?format=json"}, "congress": 117, "constitutionalAuthorityStatementText": "<pre>\n[Congressional Record Volume 168, Number 134 (Tuesday, August 9, 2022)]\n[House]\nFrom the Congressional Record Online through the Government Publishing Office [<a href=\"https://www.gpo.gov\">www.gpo.gov</a>]\nBy Mr. GROTHMAN:\nH.R. 8690.\nCongress has the power to enact this legislation pursuant\nto the following:\nArticle I Section VIII\n[Page H7557]\n</pre>", "introducedDate": "2022-08-09", "latestAction": {"actionDate": "2022-08-09", "text": "Referred to the House Committee on Education and Labor."}, "number": "8690", "originChamber": "House", "originChamberCode": "H", "policyArea": {"name": "Labor and Employment"}, "sponsors": [{"bioguideId": "G000576", "district": 6, "firstName": "Glenn", "fullName": "Rep. Grothman, Glenn [R-WI-6]", "isByRequest": "N", "lastName": "Grothman", "party": "R", "state": "WI", "url": "https://api.congress.gov/v3/member/G000576?format=json"}], "subjects": {"count": 1, "url": "https://api.congress.gov/v3/bill/117/hr/8690/subjects?format=json"}, "summaries": {"count": 1, "url": "https://api.congress.gov/v3/bill/117/hr/8690/summaries?format=json"}, "textVersions": {"count": 1, "url": "https://api.congress.gov/v3/bill/117/hr/8690/text?format=json"}, "title": "Age Discrimination in Employment Parity Act of 2022", "titles": {"count": 3, "url": "https://api.congress.gov/v3/bill/117/hr/8690/titles?format=json"}, "type": "HR", "updateDate": "2024-02-06T18:49:25Z", "updateDateIncludingText": "2024-02-06T18:49:25Z"}