{"actions": {"count": 3, "url": "https://api.congress.gov/v3/bill/117/hr/9298/actions?format=json"}, "committees": {"count": 1, "url": "https://api.congress.gov/v3/bill/117/hr/9298/committees?format=json"}, "congress": 117, "introducedDate": "2022-11-15", "latestAction": {"actionDate": "2022-11-15", "text": "Referred to the House Committee on Education and Labor."}, "number": "9298", "originChamber": "House", "originChamberCode": "H", "policyArea": {"name": "Labor and Employment"}, "sponsors": [{"bioguideId": "C001104", "district": 11, "firstName": "Madison", "fullName": "Rep. Cawthorn, Madison [R-NC-11]", "isByRequest": "N", "lastName": "Cawthorn", "party": "R", "state": "NC", "url": "https://api.congress.gov/v3/member/C001104?format=json"}], "subjects": {"count": 1, "url": "https://api.congress.gov/v3/bill/117/hr/9298/subjects?format=json"}, "summaries": {"count": 1, "url": "https://api.congress.gov/v3/bill/117/hr/9298/summaries?format=json"}, "textVersions": {"count": 1, "url": "https://api.congress.gov/v3/bill/117/hr/9298/text?format=json"}, "title": "To direct the Secretary of Labor to conduct a study on implementing a process through which a State or business may apply for an exemption from enforcement of certain occupational safety and health standards on the basis of economic hardship, and for other purposes.", "titles": {"count": 2, "url": "https://api.congress.gov/v3/bill/117/hr/9298/titles?format=json"}, "type": "HR", "updateDate": "2024-02-06T18:49:25Z", "updateDateIncludingText": "2024-02-06T18:49:25Z"}