{"actions": {"count": 3, "url": "https://api.congress.gov/v3/bill/117/hr/9436/actions?format=json"}, "committees": {"count": 1, "url": "https://api.congress.gov/v3/bill/117/hr/9436/committees?format=json"}, "congress": 117, "introducedDate": "2022-12-06", "latestAction": {"actionDate": "2022-12-06", "text": "Referred to the House Committee on Oversight and Reform."}, "number": "9436", "originChamber": "House", "originChamberCode": "H", "policyArea": {"name": "Government Operations and Politics"}, "sponsors": [{"bioguideId": "G000595", "district": 5, "firstName": "Bob", "fullName": "Rep. Good, Bob [R-VA-5]", "isByRequest": "N", "lastName": "Good", "party": "R", "state": "VA", "url": "https://api.congress.gov/v3/member/G000595?format=json"}], "subjects": {"count": 1, "url": "https://api.congress.gov/v3/bill/117/hr/9436/subjects?format=json"}, "summaries": {"count": 1, "url": "https://api.congress.gov/v3/bill/117/hr/9436/summaries?format=json"}, "textVersions": {"count": 1, "url": "https://api.congress.gov/v3/bill/117/hr/9436/text?format=json"}, "title": "To codify the Department of Labor rule regarding religious exemptions to the equal opportunity clause, and for other purposes.", "titles": {"count": 2, "url": "https://api.congress.gov/v3/bill/117/hr/9436/titles?format=json"}, "type": "HR", "updateDate": "2024-02-07T13:33:49Z", "updateDateIncludingText": "2024-02-07T13:33:49Z"}