{"actions": {"count": 3, "url": "https://api.congress.gov/v3/bill/117/hr/9508/actions?format=json"}, "committees": {"count": 1, "url": "https://api.congress.gov/v3/bill/117/hr/9508/committees?format=json"}, "congress": 117, "cosponsors": {"count": 7, "countIncludingWithdrawnCosponsors": 7, "url": "https://api.congress.gov/v3/bill/117/hr/9508/cosponsors?format=json"}, "introducedDate": "2022-12-13", "latestAction": {"actionDate": "2022-12-13", "text": "Referred to the House Committee on Foreign Affairs."}, "number": "9508", "originChamber": "House", "originChamberCode": "H", "policyArea": {"name": "International Affairs"}, "relatedBills": {"count": 1, "url": "https://api.congress.gov/v3/bill/117/hr/9508/relatedbills?format=json"}, "sponsors": [{"bioguideId": "G000579", "district": 8, "firstName": "Mike", "fullName": "Rep. Gallagher, Mike [R-WI-8]", "isByRequest": "N", "lastName": "Gallagher", "party": "R", "state": "WI", "url": "https://api.congress.gov/v3/member/G000579?format=json"}], "subjects": {"count": 1, "url": "https://api.congress.gov/v3/bill/117/hr/9508/subjects?format=json"}, "summaries": {"count": 1, "url": "https://api.congress.gov/v3/bill/117/hr/9508/summaries?format=json"}, "textVersions": {"count": 1, "url": "https://api.congress.gov/v3/bill/117/hr/9508/text?format=json"}, "title": "ANTI-SOCIAL CCP Act", "titles": {"count": 4, "url": "https://api.congress.gov/v3/bill/117/hr/9508/titles?format=json"}, "type": "HR", "updateDate": "2024-02-07T11:38:03Z", "updateDateIncludingText": "2024-02-07T11:38:03Z"}